Workbook

Sheet Summary
A1: Antelope Park Mutual Water Co
A2: Financial Summary - multi-year overview (USD)
A3: Entity ID: cawc_0100 | Fiscal year ends December 31.
A5: Presentation standard: every figure on the statement tabs is verified to its source filing and shown clean. A cell the filing does not report reads "not reported" (never estimated, never guessed).
A6: Citations, confidence tiers, and the filed-vs-computed tie-out checks live on the "Sources & audit" tab, keyed by cell, so every number is fully traceable without cluttering the statements. These pages are ready to use as filed.
A8: Metric | B8: FY2020 | C8: FY2021 | D8: FY2022 | E8: FY2023 | F8: FY2024 | G8: FY2025
A9: Operating results (USD)
A10: Total revenue | B10: 135798 | C10: 133880 | D10: 132123 | E10: 124413 | F10: 118296 | G10: 122235
A11: Total expenses | B11: 126461 | C11: 120359 | D11: 137632 | E11: 128319 | F11: 123748 | G11: 119210
A12: Net income | B12: 9337 | C12: 13521 | D12: -5509 | E12: -3906 | F12: -5452 | G12: 3025
A14: Financial position (USD, end of year)
A15: Total assets | B15: 451606 | C15: 464228 | D15: 458719 | E15: 454813 | F15: 449676 | G15: 452764
A16: Total liabilities | B16: 899 | F16: 315 | G16: 378
A17: Net assets | B17: 450707 | C17: 464228 | D17: 458719 | E17: 454813 | F17: 449361 | G17: 452386
A19: Headline ratios
A20: Operating margin | B20: 0.068756535 | C20: 0.10099343 | D20: -0.041695995 | E20: -0.031395433 | F20: -0.04608778 | G20: 0.024747413
A21: Revenue growth (YoY)
A22: Return on assets | B22: 0.020675102 | C22: 0.029125774 | D22: -0.012009531 | E22: -0.008588145 | F22: -0.012124285 | G22: 0.0066811849
A24: Figures as reported in source filings (full provenance on the Sources & audit tab). Parentheses denote negatives; ratios are computed upstream in financials_annual.

Sheet Notes
A1: Notes
A2: Human annotations from the versioned store (data/notes/). Annotations only: they never change a reported figure or a confidence tier.
A4: Date | B4: Tag | C4: Author | D4: Note
A5: No notes recorded yet.

Sheet Financial Statements
A1: Antelope Park Mutual Water Co
A2: Financial Statements - income statement, balance sheet, cash flow, member income test (USD)
A3: Entity ID: cawc_0100 | Fiscal year ends December 31.
A5: INCOME STATEMENT - as reported (USD)
A6: Line item | B6: FY2020 | C6: FY2021 | D6: FY2022 | E6: FY2023 | F6: FY2024 | G6: FY2025
A7: Revenue
A8: Program service revenue
A9: Investment income
A10: Net rental income
A11: Net gain/(loss) on investment sales
A12: Other revenue
A13: Contributions & grants
A14: Total revenue
A16: Expenses
A17: Depreciation
A18: Interest expense
A19: Total expenses | B19: 126461 | C19: 120359 | D19: 137632 | E19: 128319 | F19: 123748 | G19: 119210
A21: Net income | B21: 9337 | C21: 13521 | D21: -5509 | E21: -3906 | F21: -5452 | G21: 3025
A24: BALANCE SHEET - as reported (USD, end of year)
A25: Line item | B25: FY2020 | C25: FY2021 | D25: FY2022 | E25: FY2023 | F25: FY2024 | G25: FY2025
A26: Assets
A27: Cash | B27: 401122 | C27: 422877 | D27: 426282 | E27: 426576 | F27: 423344 | G27: 426984
A28: Savings & temporary investments
A29: Accounts receivable
A30: Inventories
A31: Prepaid expenses
A32: Property, plant & equipment (gross)
A33: Less: accumulated depreciation
A34: Net property, plant & equipment | B34: 25290 | C34: 25290 | D34: 25290 | E34: 25290 | F34: 25290 | G34: 25290
A35: Total assets | B35: 451606 | C35: 464228 | D35: 458719 | E35: 454813 | F35: 449676 | G35: 452764
A37: Liabilities
A38: Accounts payable
A39: Mortgages & notes payable
A40: Total liabilities | B40: 899 | F40: 315 | G40: 378
A42: Net Assets / Equity
A43: Capital stock
A44: Paid-in capital
A45: Retained earnings
A46: Net assets | B46: 450707 | C46: 464228 | D46: 458719 | E46: 454813 | F46: 449361 | G46: 452386
A49: CASH FLOW - derived proxy (USD)
A50: Proxy line | B50: FY2020 | C50: FY2021 | D50: FY2022 | E50: FY2023 | F50: FY2024 | G50: FY2025
A51: Operating
A52: Net income | B52: 9337 | C52: 13521 | D52: -5509 | E52: -3906 | F52: -5452 | G52: 3025
A53: + Depreciation (reported)
A54: − Δ Accounts receivable
A55: − Δ Inventories
A56: − Δ Prepaid expenses
A57: + Δ Accounts payable
A58: Operating cash flow proxy | C58: 13521 | D58: -5509 | E58: -3906 | F58: -5452 | G58: 3025
A60: Investing
A61: − Δ PP&E gross (capex proxy)
A63: Financing
A64: Δ Mortgages & notes payable
A66: Reconciliation
A67: Δ Cash + temp. investments (actual) | C67: 21755 | D67: 3405 | E67: 294 | F67: -3232 | G67: 3640
A69: Income statement and balance sheet are as reported in source filings (full provenance on the Sources & audit tab). The cash flow block is a PROXY: the filings contain no statement of cash flows, so it is derived from net income, reported depreciation, and year-over-year balance-sheet changes - treat as directional. The earliest year has no prior period, so its delta cells are blank. Parentheses denote negatives.

Sheet Balance Sheet
A1: Antelope Park Mutual Water Co
A2: Balance Sheet - as reported (USD, end of year)
A3: Entity ID: cawc_0100 | Fiscal year ends December 31.
A5: Line item | B5: FY2020 | C5: FY2021 | D5: FY2022 | E5: FY2023 | F5: FY2024 | G5: FY2025
A6: Assets
A7: Cash | B7: 401122 | C7: 422877 | D7: 426282 | E7: 426576 | F7: 423344 | G7: 426984
A8: Savings & temporary investments
A9: Accounts receivable
A10: Inventories
A11: Prepaid expenses
A12: Property, plant & equipment (gross)
A13: Less: accumulated depreciation
A14: Net property, plant & equipment | B14: 25290 | C14: 25290 | D14: 25290 | E14: 25290 | F14: 25290 | G14: 25290
A15: Total assets | B15: 451606 | C15: 464228 | D15: 458719 | E15: 454813 | F15: 449676 | G15: 452764
A17: Liabilities
A18: Accounts payable
A19: Mortgages & notes payable
A20: Total liabilities | B20: 899 | F20: 315 | G20: 378
A22: Net Assets / Equity
A23: Capital stock
A24: Paid-in capital
A25: Retained earnings
A26: Net assets | B26: 450707 | C26: 464228 | D26: 458719 | E26: 454813 | F26: 449361 | G26: 452386
A28: Balance check (assets − liab. − net assets) | B28: 0 | C28: 0 | D28: 0 | E28: 0 | F28: 0 | G28: 0
A30: Net PP&E is the reported ppe_net column (gross less accumulated depreciation). The balance check should be ~0 where all three totals are reported; a non-zero value flags a reporting or extraction discrepancy worth reviewing.

Sheet Form 990-EZ Parts I & II
A1: Antelope Park Mutual Water Co
A2: Form 990-EZ - Part I (revenue, expenses, net assets) and Part II (balance sheet), as filed (USD)
A3: Entity ID: cawc_0100 | Fiscal year ends December 31.
A5: Form 990-EZ line | B5: FY2020 | C5: FY2021 | D5: FY2022 | E5: FY2023 | F5: FY2024 | G5: FY2025
A6: Revenue (Part I)
A7: 4. Investment income | B7: 83 | C7: 38 | D7: 63 | E7: 382 | F7: 43 | G7: 43
A8: 9. Total revenue | B8: 135798 | C8: 133880 | D8: 132123 | E8: 124413 | F8: 118296 | G8: 122235
A10: Expenses (Part I)
A11: 12. Salaries, other compensation, benefits | B11: 91036 | C11: 91315 | D11: 93273 | E11: 93262 | F11: 97267 | G11: 93591
A12: 13. Fees for services (independent contractors) | B12: 7219 | C12: 6867 | D12: 8304 | E12: 5421 | F12: 4809 | G12: 4232
A13: 14. Occupancy, rent, utilities, maintenance | B13: not reported | C13: not reported | D13: not reported | E13: not reported | F13: 223 | G13: 248
A14: 15. Printing, publications, postage | B14: 1179 | C14: 1490 | D14: 1489 | E14: 1380 | F14: 1520 | G14: 1675
A15: 16. Other expenses | B15: 27027 | C15: 20687 | D15: 34566 | E15: 28256 | F15: 19929 | G15: 19464
A16: 17. Total expenses | B16: =SUM(B11:B15) | C16: =SUM(C11:C15) | D16: =SUM(D11:D15) | E16: =SUM(E11:E15) | F16: =SUM(F11:F15) | G16: =SUM(G11:G15)
A18: Net-assets reconciliation (Part I)
A19: 19. Net assets or fund balances, beginning of year | B19: 441370 | C19: 450707 | D19: 464228 | E19: 458719 | F19: 454813 | G19: 449361
A20: 18. Excess or (deficit) for the year | B20: 9337 | C20: 13521 | D20: -5509 | E20: -3906 | F20: -5452 | G20: 3025
A21: 21. Net assets or fund balances, end of year | B21: =SUM(B19,B20) | C21: =SUM(C19,C20) | D21: =SUM(D19,D20) | E21: =SUM(E19,E20) | F21: =SUM(F19,F20) | G21: =SUM(G19,G20)
A23: Balance sheet (Part II, end of year - column B)
A24: 22. Cash, savings, and investments | B24: 401122 | C24: 422877 | D24: 426282 | E24: 426576 | F24: 423344 | G24: 426984
A25: 23. Land and buildings | B25: 25290 | C25: 25290 | D25: 25290 | E25: 25290 | F25: 25290 | G25: 25290
A26: 24. Other assets | B26: 25194 | C26: 16061 | D26: 7147 | E26: 2947 | F26: 1042 | G26: 490
A27: 25. Total assets | B27: =SUM(B24:B26) | C27: =SUM(C24:C26) | D27: =SUM(D24:D26) | E27: =SUM(E24:E26) | F27: =SUM(F24:F26) | G27: =SUM(G24:G26)
A28: 26. Total liabilities | B28: 899 | C28: not reported | D28: not reported | E28: not reported | F28: 315 | G28: 378
A29: 27. Net assets or fund balances | B29: 450707 | C29: 464228 | D29: 458719 | E29: 454813 | F29: 449361 | G29: 452386
A31: Form 990-EZ is the short form: revenue and expenses are on Part I and the balance sheet is the six-line Part II (no full-990 Parts VII-XI). Total expenses (line 17) and Total assets (line 25) are live SUMs of the lines above; Total revenue (line 9) is shown as filed because the EZ nets its lines 5-7 (sales of assets, gaming, inventory) into line 9 without itemizing them. Ending net assets (line 21) is recomputed live as beginning net assets (line 19) plus the excess or deficit (line 18); where the filer's own line 21 does not equal that sum, the variance is flagged red on the Sources & audit tab and carried exactly as filed, not reconciled. Every figure's citation and confidence are on the Sources & audit tab.

Sheet Cash flow proxies
A1: Antelope Park Mutual Water Co
A2: Cash Flow Proxies - derived (USD)
A3: Entity ID: cawc_0100 | Fiscal year ends December 31.
A5: PROXY ONLY. The source filings contain no statement of cash flows. Lines below are derived from the reported income statement and year-over-year balance-sheet changes; treat as directional estimates, not GAAP cash flows. The earliest year has no prior period, so its delta cells are blank.
A7: Proxy line (USD) | B7: FY2020 | C7: FY2021 | D7: FY2022 | E7: FY2023 | F7: FY2024 | G7: FY2025
A8: Operating
A9: Net income | B9: 9337 | C9: 13521 | D9: -5509 | E9: -3906 | F9: -5452 | G9: 3025
A10: + Depreciation (reported)
A11: − Δ Accounts receivable
A12: − Δ Inventories
A13: − Δ Prepaid expenses
A14: + Δ Accounts payable
A15: Operating cash flow proxy | C15: 13521 | D15: -5509 | E15: -3906 | F15: -5452 | G15: 3025
A17: Investing
A18: − Δ PP&E gross (capex proxy)
A20: Financing
A21: Δ Mortgages & notes payable
A23: Reconciliation
A24: Δ Cash + temp. investments (actual) | C24: 21755 | D24: 3405 | E24: 294 | F24: -3232 | G24: 3640
A26: The capex proxy assumes gross PP&E rises only via capital spending (it ignores disposals). 'Δ Cash + temp. investments (actual)' is the real reported change in liquid funds and is the most reliable line here; the operating/investing/financing proxies will not perfectly reconcile to it.

Sheet Ratios
A1: Antelope Park Mutual Water Co
A2: Financial Ratios
A3: Entity ID: cawc_0100 | Fiscal year ends December 31.
A5: Ratio | B5: FY2020 | C5: FY2021 | D5: FY2022 | E5: FY2023 | F5: FY2024 | G5: FY2025
A6: Profitability (computed upstream)
A7: Operating margin (NI / revenue) | B7: 0.068756535 | C7: 0.10099343 | D7: -0.041695995 | E7: -0.031395433 | F7: -0.04608778 | G7: 0.024747413
A8: Expense ratio (expenses / revenue) | B8: 0.93124346 | C8: 0.89900657 | D8: 1.041696 | E8: 1.0313954 | F8: 1.0460878 | G8: 0.97525259
A9: Return on assets (NI / assets) | B9: 0.020675102 | C9: 0.029125774 | D9: -0.012009531 | E9: -0.008588145 | F9: -0.012124285 | G9: 0.0066811849
A10: Revenue growth (YoY)
A12: Leverage & solvency
A13: Debt-to-assets (liab. / assets) | B13: 0.0019906733 | F13: 0.00070050436 | G13: 0.00083487203
A14: Equity ratio (net assets / assets) | B14: 0.99800933 | C14: 1 | D14: 1 | E14: 1 | F14: 0.9992995 | G14: 0.99916513
A16: Liquidity & asset profile (derived here)
A17: Current ratio (current assets / AP)
A18: Cash ratio ((cash+temp inv.) / total liab.) | B18: 446.18687 | F18: 1343.9492 | G18: 1129.5873
A19: Asset age proxy (accum. deprec. / gross PP&E)
A21: Upstream ratios are read from financials_annual; derived ratios are computed only where inputs are reported. Current ratio uses accounts payable as the current-liability proxy (the filings do not split current vs. long-term liabilities). Asset age proxy: a higher % implies older / more depreciated infrastructure.

Sheet Unit economics
A1: Antelope Park Mutual Water Co
A2: Unit economics - per-customer revenue by category (USD)
A3: Entity ID: cawc_0100 | Fiscal year ends December 31.
A5: Every metric here is PER CUSTOMER (a metered service connection). It is not a per-member figure; the member (shareholder) count is a different denominator, shown in the denominator block. The visible cell shows the value and its classification; the numerator, denominator, formula, and rationale are in each metric's LOGIC popup.
A6: Per-customer denominator (service connections) | C6: State Water Board eAR Section 4
A7: Total annual revenue (eAR Section 8b B1.8) | C7: eAR Section 8b total annual revenue not reported for this system.
A8: Primary source
A10: Revenue categories (value, classification, per customer, share)
A11: Revenue category | B11: Classification | C11: Value (USD) | D11: Per customer | E11: Share of revenue
A12: Water sales revenue | B12: not reported | C12: not reported | D12: not reported | E12: not reported
A13: Assessment revenue (990 program-service revenue not matched to eAR water-rate revenue) | B13: IMPOSSIBLE | C13: IMPOSSIBLE | D13: IMPOSSIBLE | E13: IMPOSSIBLE
A14: Meter revenue | B14: not reported | C14: not reported | D14: not reported | E14: not reported
A15: Overage or tiered penalty revenue | B15: not reported | C15: not reported | D15: not reported | E15: not reported
A17: Water sales revenue - not reported
A18: Not reported: this system filed an eAR but no Section 8b revenue block, so there is no filed water-sales figure. Not fallen back to a different year.
A19: Reason: No filed eAR Section 8b water-rate revenue for this system.
A21: Assessment revenue (990 program-service revenue not matched to eAR water-rate revenue) - IMPOSSIBLE
A22: Not computed. A period-aligned residual is not possible for this filer.
A23: Reason: Not derivable. The eAR Section 8b is reporting year None while the Form 990 fiscal year ends None; the two period ends are not aligned, so a period-aligned residual cannot be computed.
A25: Meter revenue - not reported
A26: Not reported. This category is not built because doing so would double-count.
A27: Reason: The eAR Section 8a reports a base/meter rate PRICE, but the filing carries no meter revenue line and no tier volume, and the base charge is already inside the water-sales revenue (eAR Section 8b water rates). Building a separate meter figure would double-count. Not backed into from a total.
A29: Overage or tiered penalty revenue - not reported
A30: Not reported. This category is not built because doing so would double-count.
A31: Reason: The eAR Section 8a reports tiered/overage rate PRICES, but the filing carries no overage revenue and no tier consumption volume, and any overage billed is already inside the water-sales revenue. Building it would double-count. Not backed into from a total.

Sheet Rate structure
A1: Antelope Park Mutual Water Co
A2: Rate structure and representative bill - eAR Section 8a
A3: Entity ID: cawc_0100 | Fiscal year ends December 31.
A5: This block is a rate-schedule illustration at defined usage levels. It is NOT billed revenue and not a claim about any real customer's usage. The revenue side of unit economics is the separate Unit Economics block.
A6: No filed eAR Section 8a rate schedule is staged for this system.

Sheet Operational metrics
A1: Antelope Park Mutual Water Co
A2: Operational metrics - plant per acre, density, terrain
A3: Entity ID: cawc_0100 | Fiscal year ends December 31.
A5: Connections per acre
A6: Connections per acre | B6: 1.96 | C6: 146 connections / 74.6 acres. CA State Water Board SABL SERVICE_CONNECTIONS; Geodesic area (WGS84 spherical excess) of the SABL service-area polygon.

Sheet Supply & weather
A1: Antelope Park Mutual Water Co
A2: Supply and weather indicators (DWR water year)
A3: Entity ID: cawc_0100 | Fiscal year ends December 31.
A5: Reporting calendar: Different reporting periods. The DWR water year runs October 1 to September 30; this system's fiscal year ends December 31, so the two period ends are three months apart. Read the two side by side with that in mind. Neither series is recast: both are reported as filed. A water year is named for the calendar year it ends in, so WY2024 and FY2024 share a number without covering the same twelve months.
A7: Indicator | B7: WY2021 | C7: WY2022 | D7: WY2023 | E7: WY2024 | F7: WY2025
A8: Water-year type (Sacramento Valley) | B8: Critical | C8: Critical | D8: Wet | E8: Above Normal | F8: not reported
A9: Peak drought, county County | B9: not reported | C9: not reported | D9: not reported | E9: not reported | F9: not reported
A10: Precip, percent of normal (8-Station Index) | B10: 48 | C10: 86 | D10: 133 | E10: 96 | F10: 113
A11: Snowpack, April 1 percent of average | B11: 59% | C11: 38% | D11: 237% | E11: 110% | F11: 96%
A12: State Water Project allocation | B12: 5% | C12: 5% | D12: 100% | E12: 40% | F12: 50%

Sheet How this was built
A1: Antelope Park Mutual Water Co
A2: How this was built - forensic lineage
A3: Entity ID: cawc_0100 | Fiscal year ends December 31.
A5: A plain account of the forensic lineage behind the hard-to-source metrics: what sources were checked, what was found, what was derived, and what could not be built and why. Every figure marked DERIVED or IMPOSSIBLE above is traceable to a line here.
A7: Water-sales revenue per customer - not reported
A8: Sources checked | B8: State Water Board eAR Section 8b (water-rate revenue B1.1/B1.2); State Water Board eAR Section 4 (connection count, same reporting year); audited financial statement (secondary cross-check, where published)
A9: What was found | B9: The eAR Section 8b reports water-rate revenue for reporting year None, so this is a DIRECT filed figure; per customer it is divided by the eAR Section 4 connection count for the same reporting year, so numerator and denominator share the year.
A11: Assessment revenue (residual) - IMPOSSIBLE
A12: Sources checked | B12: Form 990 Part VIII line 2 (program-service revenue); State Water Board eAR Section 8b (water-rate revenue B1.1/B1.2); eAR Section 8b filer comment (WRRevenueComments)
A13: What was found | B13: A period-aligned residual cannot be computed for this filer, so the metric is rendered IMPOSSIBLE rather than guessed.
A14: Caveat | B14: Not derivable. The eAR Section 8b is reporting year None while the Form 990 fiscal year ends None; the two period ends are not aligned, so a period-aligned residual cannot be computed.
A16: Meter revenue - not reported
A17: Sources checked | B17: State Water Board eAR Section 8a (rate prices); State Water Board eAR Section 8b (revenue lines); audited financial statement
A18: What was found | B18: The rate price exists in Section 8a but no revenue or tier volume is reported, and the base charge is already inside water sales.
A19: Caveat | B19: The eAR Section 8a reports a base/meter rate PRICE, but the filing carries no meter revenue line and no tier volume, and the base charge is already inside the water-sales revenue (eAR Section 8b water rates). Building a separate meter figure would double-count. Not backed into from a total.
A21: Overage / tiered-penalty revenue - not reported
A22: Sources checked | B22: State Water Board eAR Section 8a (rate prices); State Water Board eAR Section 8b (revenue lines); audited financial statement
A23: What was found | B23: The rate price exists in Section 8a but no revenue or tier volume is reported, and the base charge is already inside water sales.
A24: Caveat | B24: The eAR Section 8a reports tiered/overage rate PRICES, but the filing carries no overage revenue and no tier consumption volume, and any overage billed is already inside the water-sales revenue. Building it would double-count. Not backed into from a total.
A26: eAR Section 8b reporting-period basis - sourced
A27: Sources checked | B27: eAR Section 8b B0.1 (WRFinancialReportingPeriod); eAR Section 8b B0.2 (WRFiscalYearStartDate)
A28: What was found | B28: The reporting basis (fiscal vs calendar year) is read from the filer's own B0.1/B0.2 answer and staged verbatim, never hardcoded, so the 990 comparison and the residual are period-aligned.
A30: Member (shareholder) count denominator - not reported
A31: Sources checked | B31: Form 990 (no member count stated); company website
A32: What was found | B32: No filing states a member/shareholder count, so the per-member unit economics read not reported rather than borrowing the connection count.
A34: Water volume delivered (acre-feet) - not reported
A35: Sources checked | B35: Form 990 (not in the filing); Consumer Confidence Report; eAR Section 6 (PRA-gated)
A36: What was found | B36: Volume delivered in acre-feet is not in the Form 990 and the CCR states only a source mix, so the per-acre-foot metrics read not reported; the eAR Section 6 is named as the source still needed.

Sheet Sources & audit
A1: Antelope Park Mutual Water Co
A2: Sources & audit - full provenance and tie-outs (kept off the statements so they read clean)
A3: Entity ID: cawc_0100 | Fiscal year ends December 31.
A5: Presentation standard: every figure on the statement tabs is verified to its source filing and shown clean. A cell the filing does not report reads "not reported" (never estimated, never guessed).
A6: Citations, confidence tiers, and the filed-vs-computed tie-out checks live on the "Sources & audit" tab, keyed by cell, so every number is fully traceable without cluttering the statements. These pages are ready to use as filed.
A8: A. Filing provenance (one row per staged extraction)
A9: Fiscal year | B9: Period end | C9: Filing type | D9: Confidence | E9: Extraction ID | F9: Object ID | G9: Extracted by | H9: Extracted at | I9: Source URL
A10: FY2020 | B10: 2020-12-31 | C10: 990-EZ | D10: high | E10: 7958a466-c395-486b-bdca-d415ce2ab361 | F10: 202110639349201416 | G10: claude-opus-5 | H10: 2026-09-23T07:16:52+00:00 | I10: https://apps.irs.gov/pub/epostcard/990/xml/2021/2021_TEOS_XML_01A.zip#202110639349201416_public.xml
A11: FY2021 | B11: 2021-12-31 | C11: 990-EZ | D11: high | E11: ca001562-89e0-4a34-94be-0dc9fbba1373 | F11: 202201039349201405 | G11: claude-opus-5 | H11: 2026-09-23T07:16:52+00:00 | I11: https://apps.irs.gov/pub/epostcard/990/xml/2022/2022_TEOS_XML_01A.zip#202201039349201405_public.xml
A12: FY2022 | B12: 2022-12-31 | C12: 990-EZ | D12: high | E12: 9f749a81-ef49-4566-869f-b724c06981aa | F12: 202310419349201006 | G12: claude-opus-5 | H12: 2026-09-23T07:16:52+00:00 | I12: https://apps.irs.gov/pub/epostcard/990/xml/2023/2023_TEOS_XML_02A.zip#202310419349201006_public.xml
A13: FY2023 | B13: 2023-12-31 | C13: 990-EZ | D13: high | E13: e6daa14b-72c1-4990-9eb2-25d2f37f26be | F13: 202400589349200225 | G13: claude-opus-5 | H13: 2026-09-23T07:16:52+00:00 | I13: https://apps.irs.gov/pub/epostcard/990/xml/2024/2024_TEOS_XML_03A.zip#202400589349200225_public.xml
A14: FY2024 | B14: 2024-12-31 | C14: 990-EZ | D14: high | E14: 5d5e9f51-0bd3-4db6-94cb-58f95d797d01 | F14: 202520419349200622 | G14: claude-opus-5 | H14: 2026-09-23T07:16:52+00:00 | I14: https://apps.irs.gov/pub/epostcard/990/xml/2025/2025_TEOS_XML_02A.zip#202520419349200622_public.xml
A15: FY2025 | B15: 2025-12-31 | C15: 990-EZ | D15: high | E15: 5827772c-b6ae-4014-95dd-cd2d20924cb1 | F15: 202640489349201719 | G15: claude-opus-5 | H15: 2026-09-23T07:16:52+00:00 | I15: https://apps.irs.gov/pub/epostcard/990/xml/2026/2026_TEOS_XML_02A.zip#202640489349201719_public.xml
A17: B. Figure citations (every figure on the statement tabs, keyed by cell)
A18: Tab | B18: Cell | C18: Line item | D18: Form 990 line | E18: Key path | F18: Confidence | G18: As filed
A19: Form 990-EZ Parts I & II | B19: B7 | C19: 4. Investment income | D19: Part I line 4 | E19: part_i_revenue_expenses.investment_income | F19: high | G19: 83
A20: Form 990-EZ Parts I & II | B20: C7 | C20: 4. Investment income | D20: Part I line 4 | E20: part_i_revenue_expenses.investment_income | F20: high | G20: 38
A21: Form 990-EZ Parts I & II | B21: D7 | C21: 4. Investment income | D21: Part I line 4 | E21: part_i_revenue_expenses.investment_income | F21: high | G21: 63
A22: Form 990-EZ Parts I & II | B22: E7 | C22: 4. Investment income | D22: Part I line 4 | E22: part_i_revenue_expenses.investment_income | F22: high | G22: 382
A23: Form 990-EZ Parts I & II | B23: F7 | C23: 4. Investment income | D23: Part I line 4 | E23: part_i_revenue_expenses.investment_income | F23: high | G23: 43
A24: Form 990-EZ Parts I & II | B24: G7 | C24: 4. Investment income | D24: Part I line 4 | E24: part_i_revenue_expenses.investment_income | F24: high | G24: 43
A25: Form 990-EZ Parts I & II | B25: B8 | C25: 9. Total revenue | D25: Part I line 9 | E25: part_i_revenue_expenses.total_revenue | F25: high | G25: 135798
A26: Form 990-EZ Parts I & II | B26: C8 | C26: 9. Total revenue | D26: Part I line 9 | E26: part_i_revenue_expenses.total_revenue | F26: high | G26: 133880
A27: Form 990-EZ Parts I & II | B27: D8 | C27: 9. Total revenue | D27: Part I line 9 | E27: part_i_revenue_expenses.total_revenue | F27: high | G27: 132123
A28: Form 990-EZ Parts I & II | B28: E8 | C28: 9. Total revenue | D28: Part I line 9 | E28: part_i_revenue_expenses.total_revenue | F28: high | G28: 124413
A29: Form 990-EZ Parts I & II | B29: F8 | C29: 9. Total revenue | D29: Part I line 9 | E29: part_i_revenue_expenses.total_revenue | F29: high | G29: 118296
A30: Form 990-EZ Parts I & II | B30: G8 | C30: 9. Total revenue | D30: Part I line 9 | E30: part_i_revenue_expenses.total_revenue | F30: high | G30: 122235
... A95: Form 990-EZ Parts I & II | B95: G29 | C95: 27. Net assets or fund balances | D95: Part II line 27 col B | E95: part_ii_balance_sheet.net_assets_eoy | F95: high | G95: 452386
A97: C. Tie-out checks (filed vs computed; any nonzero variance is flagged red)
A98: Tab | B98: Check | C98: Fiscal year | D98: Filed | E98: Computed | F98: Variance (computed - filed)
A99: Form 990-EZ Parts I & II | B99: 17. Total expenses | C99: FY2020 | D99: 126461 | E99: ='Form 990-EZ Parts I & II'!B16 | F99: =E99-D99
A100: Form 990-EZ Parts I & II | B100: 17. Total expenses | C100: FY2021 | D100: 120359 | E100: ='Form 990-EZ Parts I & II'!C16 | F100: =E100-D100
A101: Form 990-EZ Parts I & II | B101: 17. Total expenses | C101: FY2022 | D101: 137632 | E101: ='Form 990-EZ Parts I & II'!D16 | F101: =E101-D101
A102: Form 990-EZ Parts I & II | B102: 17. Total expenses | C102: FY2023 | D102: 128319 | E102: ='Form 990-EZ Parts I & II'!E16 | F102: =E102-D102
A103: Form 990-EZ Parts I & II | B103: 17. Total expenses | C103: FY2024 | D103: 123748 | E103: ='Form 990-EZ Parts I & II'!F16 | F103: =E103-D103
A104: Form 990-EZ Parts I & II | B104: 17. Total expenses | C104: FY2025 | D104: 119210 | E104: ='Form 990-EZ Parts I & II'!G16 | F104: =E104-D104
A105: Form 990-EZ Parts I & II | B105: 21. Net assets or fund balances, end of year | C105: FY2020 | D105: 450707 | E105: ='Form 990-EZ Parts I & II'!B21 | F105: =E105-D105
A106: Form 990-EZ Parts I & II | B106: 21. Net assets or fund balances, end of year | C106: FY2021 | D106: 464228 | E106: ='Form 990-EZ Parts I & II'!C21 | F106: =E106-D106
A107: Form 990-EZ Parts I & II | B107: 21. Net assets or fund balances, end of year | C107: FY2022 | D107: 458719 | E107: ='Form 990-EZ Parts I & II'!D21 | F107: =E107-D107
A108: Form 990-EZ Parts I & II | B108: 21. Net assets or fund balances, end of year | C108: FY2023 | D108: 454813 | E108: ='Form 990-EZ Parts I & II'!E21 | F108: =E108-D108
A109: Form 990-EZ Parts I & II | B109: 21. Net assets or fund balances, end of year | C109: FY2024 | D109: 449361 | E109: ='Form 990-EZ Parts I & II'!F21 | F109: =E109-D109
A110: Form 990-EZ Parts I & II | B110: 21. Net assets or fund balances, end of year | C110: FY2025 | D110: 452386 | E110: ='Form 990-EZ Parts I & II'!G21 | F110: =E110-D110
A111: Form 990-EZ Parts I & II | B111: 25. Total assets | C111: FY2020 | D111: 451606 | E111: ='Form 990-EZ Parts I & II'!B27 | F111: =E111-D111
A112: Form 990-EZ Parts I & II | B112: 25. Total assets | C112: FY2021 | D112: 464228 | E112: ='Form 990-EZ Parts I & II'!C27 | F112: =E112-D112
A113: Form 990-EZ Parts I & II | B113: 25. Total assets | C113: FY2022 | D113: 458719 | E113: ='Form 990-EZ Parts I & II'!D27 | F113: =E113-D113
A114: Form 990-EZ Parts I & II | B114: 25. Total assets | C114: FY2023 | D114: 454813 | E114: ='Form 990-EZ Parts I & II'!E27 | F114: =E114-D114
A115: Form 990-EZ Parts I & II | B115: 25. Total assets | C115: FY2024 | D115: 449676 | E115: ='Form 990-EZ Parts I & II'!F27 | F115: =E115-D115
A116: Form 990-EZ Parts I & II | B116: 25. Total assets | C116: FY2025 | D116: 452764 | E116: ='Form 990-EZ Parts I & II'!G27 | F116: =E116-D116
A117: Form 990-EZ Parts I & II | B117: Balance sheet identity: line 25 = line 26 + line 27 (EOY) | C117: FY2020 | D117: ='Form 990-EZ Parts I & II'!B27 | E117: =SUM('Form 990-EZ Parts I & II'!B28,'Form 990-EZ Parts I & II'!B29) | F117: =E117-D117
A118: Form 990-EZ Parts I & II | B118: Balance sheet identity: line 25 = line 26 + line 27 (EOY) | C118: FY2021 | D118: ='Form 990-EZ Parts I & II'!C27 | E118: =SUM('Form 990-EZ Parts I & II'!C28,'Form 990-EZ Parts I & II'!C29) | F118: =E118-D118
A119: Form 990-EZ Parts I & II | B119: Balance sheet identity: line 25 = line 26 + line 27 (EOY) | C119: FY2022 | D119: ='Form 990-EZ Parts I & II'!D27 | E119: =SUM('Form 990-EZ Parts I & II'!D28,'Form 990-EZ Parts I & II'!D29) | F119: =E119-D119
A120: Form 990-EZ Parts I & II | B120: Balance sheet identity: line 25 = line 26 + line 27 (EOY) | C120: FY2023 | D120: ='Form 990-EZ Parts I & II'!E27 | E120: =SUM('Form 990-EZ Parts I & II'!E28,'Form 990-EZ Parts I & II'!E29) | F120: =E120-D120
A121: Form 990-EZ Parts I & II | B121: Balance sheet identity: line 25 = line 26 + line 27 (EOY) | C121: FY2024 | D121: ='Form 990-EZ Parts I & II'!F27 | E121: =SUM('Form 990-EZ Parts I & II'!F28,'Form 990-EZ Parts I & II'!F29) | F121: =E121-D121
A122: Form 990-EZ Parts I & II | B122: Balance sheet identity: line 25 = line 26 + line 27 (EOY) | C122: FY2025 | D122: ='Form 990-EZ Parts I & II'!G27 | E122: =SUM('Form 990-EZ Parts I & II'!G28,'Form 990-EZ Parts I & II'!G29) | F122: =E122-D122
A124: D. Preparer / auditor trail (one row per fiscal year, as filed)
A125: Fiscal year | B125: Paid preparer | C125: Preparer firm | D125: Independent auditor | E125: Citation
A126: FY2020 | B126: Mayank Madhavani CPA | C126: BURKEY COX EVANS & BRADFORD | D126: not reported | E126: Form 990 Return Header, Paid Preparer block (return_header.preparer_person_name / preparer_firm_name); auditor: Part XII line 2 reports audited financial statements but does not name the firm.
A127: FY2021 | B127: Mayank Madhavani CPA | C127: BURKEY COX EVANS & BRADFORD | D127: not reported | E127: Form 990 Return Header, Paid Preparer block (return_header.preparer_person_name / preparer_firm_name); auditor: Part XII line 2 reports audited financial statements but does not name the firm.
A128: FY2022 | B128: Mayank Madhavani CPA-PFS CFP | C128: BURKEY COX EVANS & BRADFORD | D128: not reported | E128: Form 990 Return Header, Paid Preparer block (return_header.preparer_person_name / preparer_firm_name); auditor: Part XII line 2 reports audited financial statements but does not name the firm.
A129: FY2023 | B129: Mayank Madhavani CPA-PFS CFP | C129: BURKEY COX EVANS & BRADFORD | D129: not reported | E129: Form 990 Return Header, Paid Preparer block (return_header.preparer_person_name / preparer_firm_name); auditor: Part XII line 2 reports audited financial statements but does not name the firm.
A130: FY2024 | B130: Mayank Madhavani CPA-PFS CFP | C130: BURKEY COX EVANS & BRADFORD | D130: not reported | E130: Form 990 Return Header, Paid Preparer block (return_header.preparer_person_name / preparer_firm_name); auditor: Part XII line 2 reports audited financial statements but does not name the firm.
A131: FY2025 | B131: Mayank Madhavani CPA-PFS CFP | C131: BURKEY COX EVANS & BRADFORD | D131: not reported | E131: Form 990 Return Header, Paid Preparer block (return_header.preparer_person_name / preparer_firm_name); auditor: Part XII line 2 reports audited financial statements but does not name the firm.
A133: Section B lists every figure on the statement tabs by its cell, so any number can be traced to its Form 990 line, key path, and confidence without cluttering the statements. Section C recomputes each statutory total live from the statement cells and compares it with the as-filed value; a nonzero variance turns red. A red row is a filer-internal inconsistency (e.g. an ending net-assets figure that does not equal the beginning balance plus the year's surplus or deficit), carried exactly as filed and never reconciled; the statutory totals otherwise tie to zero. Section D records the paid preparer and (where named) the auditor for each year, as filed; the 990 names the preparer but not the auditing firm, so the auditor reads "not reported". Section E lists every as-filed wording variant for Part IX line-24 rows that were consolidated across years because they differed only by capitalization or spacing. IRS efile XML has no page numbers, so 990 figures cite by Part and line (the key path), not a page.

Sheet Provenance
A1: Build provenance | B1: Built from source commit d418ffb17485 (2026-10-06); source fingerprint a75a8eee82c65cf7; 192 companies (179 retail mutual, 4 irrigation mutual, 3 mutual, no PWSID, purpose not stated, 2 frozen non-mutual (special district), 2 wholesale mutual, 1 frozen non-mutual (investor-owned), 1 frozen non-mutual (municipal)); 91 gates; build id 3d08d6d2a855.
A2: source_commit | B2: d418ffb174855ab78000d391d42f898397b0d8aa
A3: source_commit_date | B3: 2026-10-06
A4: source_fingerprint | B4: a75a8eee82c65cf7096931f06e18affdc28686a02895b46538e7298b57c04d94
A5: gate_count | B5: 91
A6: build_id | B6: 3d08d6d2a855
A7: registry: frozen non-mutual (investor-owned) | B7: 1
A8: registry: frozen non-mutual (municipal) | B8: 1
A9: registry: frozen non-mutual (special district) | B9: 2
A10: registry: irrigation mutual | B10: 4
A11: registry: mutual, no PWSID, purpose not stated | B11: 3
A12: registry: retail mutual | B12: 179
A13: registry: wholesale mutual | B13: 2
